QuickFlash/__init__.py
QuickFlash/module.py
QuickFlash-0.1.5.dist-info/METADATA
QuickFlash-0.1.5.dist-info/WHEEL
QuickFlash-0.1.5.dist-info/top_level.txt
QuickFlash-0.1.5.dist-info/RECORD
